blended/__init__.py
blended/__main__.py
blended/functions.py
blended-5.0.2.dist-info/DESCRIPTION.rst
blended-5.0.2.dist-info/METADATA
blended-5.0.2.dist-info/RECORD
blended-5.0.2.dist-info/WHEEL
blended-5.0.2.dist-info/entry_points.txt
blended-5.0.2.dist-info/metadata.json
blended-5.0.2.dist-info/top_level.txt
