Metadata-Version: 2.0
Name: blended
Version: 5.0.2
Summary: The Most Versatile Static HTML Site Generator
Home-page: http://jmroper.com/blended/
Author: John Roper
Author-email: johnroper100@gmail.com
License: GPL3.0
Platform: UNKNOWN
Requires-Dist: Markdown
Requires-Dist: click
Requires-Dist: coffeescript
Requires-Dist: colorama
Requires-Dist: cssmin
Requires-Dist: docutils
Requires-Dist: jsmin
Requires-Dist: lesscpy
Requires-Dist: libsass
Requires-Dist: mammoth
Requires-Dist: pyjade
Requires-Dist: stylus
Requires-Dist: textile
Requires-Dist: untangle
Requires-Dist: watchdog
